{"job_id": "job_20260618_061406_ba685e62", "status": "done", "phase": "Audit finalizat (10 produse).", "batch_path": "E:\\laragon\\www\\besoiupieseauto.ro/admin/storage/image_audit/batches/batch_20260618_061406.json", "batch_name": "batch_20260618_061406.json", "ids": ["d963ab5318550acf", "4a69d20a599efe0d", "eaf6405db65e1f48", "7f0b35f05a7a2900", "c5c594e6f691b511", "2914fee0a608e790", "fd68e1bbcef2bef5", "e737ba19fb0eb3e0", "9c73de976d832a60", "4e6f40cb0fa474c3"], "products": [{"randomn_id": "d963ab5318550acf", "title": "Aditiv Ulei Motor 2671", "code": "2671"}, {"randomn_id": "4a69d20a599efe0d", "title": "Ulei Cutie Automata 3659", "code": "3659"}, {"randomn_id": "eaf6405db65e1f48", "title": "Aditiv Ulei Hidraulic 5135", "code": "5135"}, {"randomn_id": "7f0b35f05a7a2900", "title": "Lubrificant Universal Bosch 5 000 000 163", "code": "5000000163"}, {"randomn_id": "c5c594e6f691b511", "title": "Olej Gm Opel 15W40 5L Olg Opel 1942050", "code": "1942050"}, {"randomn_id": "2914fee0a608e790", "title": "Vas Ulei Servo 770018", "code": "770018"}, {"randomn_id": "fd68e1bbcef2bef5", "title": "Radiator Ulei Termoflot 140011", "code": "140011"}, {"randomn_id": "e737ba19fb0eb3e0", "title": "Olej Gm Opel 10W40 1L Olg Opel GM104", "code": "GM104"}, {"randomn_id": "9c73de976d832a60", "title": "Lichid de Frana 360047", "code": "360047"}, {"randomn_id": "4e6f40cb0fa474c3", "title": "Olej Gm Opel 10W40 2L Olg Opel GM116", "code": "GM116"}], "total": 10, "done": 0, "started_at": 1781763246, "updated_at": 1781763635, "current_index": 10, "current_product_id": "4e6f40cb0fa474c3", "current_product_title": "Olej Gm Opel 10W40 2L Olg Opel GM116", "finished_at": 1781763635, "summary": "## Audit produs 10/10 \u2014 `4e6f40cb0fa474c3`\n\n**Verdict salvat:** `admin/storage/image_audit/by_product/4e6f40cb0fa474c3.json`\n\n### Ce arat\u0103 imaginea\nBidon gri **Liqui Moly MoS2 Leichtlauf 10W-40**, **1 litru** \u2014 ulei motor semisintetic (*Made in Germany*, ACEA A3/B4, API SL/CF).\n\n### Compara\u021bie cu metadata\n\n| C\u00e2mp | Potrivire |\n|------|-----------|\n| Titlu: *Olej Gm Opel 10W40 2L Olg Opel GM116* | Nu |\n| V\u00e2scozitate: *10W40* | Da \u2014 singura potrivire |\n| Volum: *2 L* | Nu \u2014 imaginea arat\u0103 **1 L** "}